jovian/__init__.py
jovian/cli.py
jovian/utils/__init__.py
jovian/utils/anaconda.py
jovian/utils/api.py
jovian/utils/clone.py
jovian/utils/constants.py
jovian/utils/credentials.py
jovian/utils/jupyter.py
jovian/utils/logger.py
jovian/utils/pip.py
jvn-0.0.6.dist-info/METADATA
jvn-0.0.6.dist-info/RECORD
jvn-0.0.6.dist-info/WHEEL
jvn-0.0.6.dist-info/entry_points.txt
jvn-0.0.6.dist-info/top_level.txt
