Metadata-Version: 2.1
Name: jvn
Version: 0.0.6
Summary: Jovian Python SDK
Home-page: https://jovian.ai/
Author: SwiftAce
Author-email: opensource@swiftace.ai
License: UNKNOWN
Platform: UNKNOWN
Classifier: Programming Language :: Python :: 3
Classifier: License :: OSI Approved :: MIT License
Classifier: Operating System :: OS Independent
Requires-Dist: requests
Requires-Dist: tqdm
